MANIFEST.in
portal_sale_data.xml
portal_sale_view.xml
res_config_view.xml
setup.py
./__init__.py
./__openerp__.py
./portal_sale.py
./res_config.py
i18n/cs.po
i18n/de.po
i18n/es.po
i18n/es_MX.po
i18n/fi.po
i18n/fr.po
i18n/hr.po
i18n/hu.po
i18n/lt.po
i18n/mk.po
i18n/mn.po
i18n/nl.po
i18n/pl.po
i18n/portal_sale.pot
i18n/pt.po
i18n/pt_BR.po
i18n/ro.po
i18n/ru.po
i18n/sl.po
i18n/sv.po
i18n/tr.po
i18n/zh_CN.po
openerp_portal_sale.egg-info/PKG-INFO
openerp_portal_sale.egg-info/SOURCES.txt
openerp_portal_sale.egg-info/dependency_links.txt
openerp_portal_sale.egg-info/requires.txt
openerp_portal_sale.egg-info/top_level.txt
security/ir.model.access.csv
security/portal_security.xml